vlmeval/__init__.py
vlmeval/__main__.py
vlmeval/config.py
vlmeval/inference.py
vlmeval/inference_mt.py
vlmeval/inference_video.py
vlmeval/run.py
vlmeval/tools.py
vlmeval/api/__init__.py
vlmeval/api/base.py
vlmeval/api/claude.py
vlmeval/api/cloudwalk.py
vlmeval/api/gemini.py
vlmeval/api/glm_vision.py
vlmeval/api/gpt.py
vlmeval/api/hf_chat_model.py
vlmeval/api/qwen_api.py
vlmeval/api/qwen_vl_api.py
vlmeval/api/reka.py
vlmeval/api/sensechat_vision.py
vlmeval/api/stepai.py
vlmeval/dataset/__init__.py
vlmeval/dataset/image_base.py
vlmeval/dataset/image_caption.py
vlmeval/dataset/image_mcq.py
vlmeval/dataset/image_mt.py
vlmeval/dataset/image_vqa.py
vlmeval/dataset/image_yorn.py
vlmeval/dataset/mmbench_video.py
vlmeval/dataset/video_base.py
vlmeval/dataset/videomme.py
vlmeval/dataset/utils/__init__.py
vlmeval/dataset/utils/judge_util.py
vlmeval/dataset/utils/llavabench.py
vlmeval/dataset/utils/mathv.py
vlmeval/dataset/utils/mathvista.py
vlmeval/dataset/utils/mmbench_video.py
vlmeval/dataset/utils/mmdu.py
vlmeval/dataset/utils/mmlongbench.py
vlmeval/dataset/utils/mmvet.py
vlmeval/dataset/utils/multiple_choice.py
vlmeval/dataset/utils/ocrbench.py
vlmeval/dataset/utils/vcr.py
vlmeval/dataset/utils/videomme.py
vlmeval/dataset/utils/vqa_eval.py
vlmeval/dataset/utils/yorn.py
vlmeval/smp/__init__.py
vlmeval/smp/file.py
vlmeval/smp/log.py
vlmeval/smp/misc.py
vlmeval/smp/vlm.py
vlmeval/utils/__init__.py
vlmeval/utils/arguments.py
vlmeval/utils/matching_util.py
vlmeval/utils/mp_util.py
vlmeval/utils/result_transfer.py
vlmeval/vlm/__init__.py
vlmeval/vlm/base.py
vlmeval/vlm/bunnyllama3.py
vlmeval/vlm/cambrian.py
vlmeval/vlm/chameleon.py
vlmeval/vlm/cogvlm.py
vlmeval/vlm/deepseek_vl.py
vlmeval/vlm/emu.py
vlmeval/vlm/idefics.py
vlmeval/vlm/instructblip.py
vlmeval/vlm/internvl_chat.py
vlmeval/vlm/mgm.py
vlmeval/vlm/minicpm_v.py
vlmeval/vlm/minigpt4.py
vlmeval/vlm/mmalaya.py
vlmeval/vlm/monkey.py
vlmeval/vlm/mplug_owl2.py
vlmeval/vlm/omnilmm.py
vlmeval/vlm/open_flamingo.py
ms_vlmeval-0.1.8.dist-info/LICENSE
ms_vlmeval-0.1.8.dist-info/METADATA
ms_vlmeval-0.1.8.dist-info/WHEEL
ms_vlmeval-0.1.8.dist-info/entry_points.txt
ms_vlmeval-0.1.8.dist-info/top_level.txt
ms_vlmeval-0.1.8.dist-info/RECORD
