Metadata-Version: 2.1
Name: ms-vlmeval
Version: 0.1.8
Summary: OpenCompass VLM Evaluation Kit
Author: Haodong Duan
Author-email: dhd.efz@gmail.com
Maintainer: Haodong Duan
Maintainer-email: dhd.efz@gmail.com
Keywords: AI,NLP,in-context learning
Classifier: Programming Language :: Python :: 3.7
Classifier: Programming Language :: Python :: 3.8
Classifier: Programming Language :: Python :: 3.9
Classifier: Programming Language :: Python :: 3.10
Classifier: Intended Audience :: Developers
Classifier: Intended Audience :: Education
Classifier: Intended Audience :: Science/Research
Requires-Python: >=3.7.0
License-File: LICENSE
Requires-Dist: einops
Requires-Dist: gradio
Requires-Dist: huggingface-hub
Requires-Dist: matplotlib
Requires-Dist: numpy >=1.23.4
Requires-Dist: omegaconf
Requires-Dist: openai ==1.3.5
Requires-Dist: opencv-python >=4.4.0.46
Requires-Dist: openpyxl
Requires-Dist: pandas
Requires-Dist: pillow
Requires-Dist: portalocker
Requires-Dist: protobuf
Requires-Dist: pycocoevalcap
Requires-Dist: python-dotenv
Requires-Dist: requests
Requires-Dist: rich
Requires-Dist: seaborn
Requires-Dist: sentencepiece
Requires-Dist: setuptools
Requires-Dist: sty
Requires-Dist: tabulate
Requires-Dist: tiktoken
Requires-Dist: timeout-decorator
Requires-Dist: torch >=2.0.1
Requires-Dist: tqdm
Requires-Dist: transformers
Requires-Dist: typing-extensions ==4.7.1
Requires-Dist: validators
Requires-Dist: visual-genome
Requires-Dist: xlsxwriter
Requires-Dist: xtuner
